Metadata-Version: 2.1
Name: VKLong
Version: 0.1.2
Summary: Simple wrapper to make VK-Bot on Longpoll API
Author: LeetCrash
Author-email: leetcrash.official@gmail.com
Keywords: vk api,vk api library,vk longpoll,vk bot,vklong,vkapi,vk long poll bot
